<?xml version="1.0" encoding="utf-8"?>
	<annotation>
		<folder>driving_annotation_dataset</folder>
		<filename>0000072_03425_d_0000004.jpg</filename>
		<size>
			<width>1360</width>
			<height>765</height>
			<depth>3</depth>
		</size>
		<object>
			<name>pedestrian</name>
			<pose>Unspecified</pose>
			<truncated>0</truncated>
			<difficult>0</difficult>
			<bndbox>
				<xmin>31</xmin>
				<ymin>47</ymin>
				<xmax>48</xmax>
				<ymax>79</ymax>
			</bndbox>
		</object>
		<object>
			<name>pedestrian</name>
			<pose>Unspecified</pose>
			<truncated>0</truncated>
			<difficult>0</difficult>
			<bndbox>
				<xmin>42</xmin>
				<ymin>40</ymin>
				<xmax>60</xmax>
				<ymax>78</ymax>
			</bndbox>
		</object>
		<object>
			<name>people</name>
			<pose>Unspecified</pose>
			<truncated>0</truncated>
			<difficult>0</difficult>
			<bndbox>
				<xmin>79</xmin>
				<ymin>33</ymin>
				<xmax>101</xmax>
				<ymax>64</ymax>
			</bndbox>
		</object>
		<object>
			<name>bicycle</name>
			<pose>Unspecified</pose>
			<truncated>0</truncated>
			<difficult>0</difficult>
			<bndbox>
				<xmin>69</xmin>
				<ymin>45</ymin>
				<xmax>110</xmax>
				<ymax>68</ymax>
			</bndbox>
		</object>
		<object>
			<name>pedestrian</name>
			<pose>Unspecified</pose>
			<truncated>0</truncated>
			<difficult>0</difficult>
			<bndbox>
				<xmin>1</xmin>
				<ymin>347</ymin>
				<xmax>22</xmax>
				<ymax>399</ymax>
			</bndbox>
		</object>
		<object>
			<name>car</name>
			<pose>Unspecified</pose>
			<truncated>0</truncated>
			<difficult>0</difficult>
			<bndbox>
				<xmin>144</xmin>
				<ymin>256</ymin>
				<xmax>256</xmax>
				<ymax>342</ymax>
			</bndbox>
		</object>
		<object>
			<name>pedestrian</name>
			<pose>Unspecified</pose>
			<truncated>0</truncated>
			<difficult>0</difficult>
			<bndbox>
				<xmin>177</xmin>
				<ymin>8</ymin>
				<xmax>190</xmax>
				<ymax>35</ymax>
			</bndbox>
		</object>
		<object>
			<name>pedestrian</name>
			<pose>Unspecified</pose>
			<truncated>0</truncated>
			<difficult>0</difficult>
			<bndbox>
				<xmin>198</xmin>
				<ymin>10</ymin>
				<xmax>213</xmax>
				<ymax>40</ymax>
			</bndbox>
		</object>
		<object>
			<name>people</name>
			<pose>Unspecified</pose>
			<truncated>0</truncated>
			<difficult>0</difficult>
			<bndbox>
				<xmin>303</xmin>
				<ymin>4</ymin>
				<xmax>314</xmax>
				<ymax>26</ymax>
			</bndbox>
		</object>
		<object>
			<name>motor</name>
			<pose>Unspecified</pose>
			<truncated>0</truncated>
			<difficult>0</difficult>
			<bndbox>
				<xmin>297</xmin>
				<ymin>11</ymin>
				<xmax>324</xmax>
				<ymax>32</ymax>
			</bndbox>
		</object>
		<object>
			<name>people</name>
			<pose>Unspecified</pose>
			<truncated>0</truncated>
			<difficult>0</difficult>
			<bndbox>
				<xmin>325</xmin>
				<ymin>2</ymin>
				<xmax>335</xmax>
				<ymax>19</ymax>
			</bndbox>
		</object>
		<object>
			<name>bicycle</name>
			<pose>Unspecified</pose>
			<truncated>0</truncated>
			<difficult>0</difficult>
			<bndbox>
				<xmin>320</xmin>
				<ymin>8</ymin>
				<xmax>340</xmax>
				<ymax>23</ymax>
			</bndbox>
		</object>
		<object>
			<name>car</name>
			<pose>Unspecified</pose>
			<truncated>0</truncated>
			<difficult>0</difficult>
			<bndbox>
				<xmin>164</xmin>
				<ymin>59</ymin>
				<xmax>259</xmax>
				<ymax>98</ymax>
			</bndbox>
		</object>
		<object>
			<name>van</name>
			<pose>Unspecified</pose>
			<truncated>0</truncated>
			<difficult>0</difficult>
			<bndbox>
				<xmin>245</xmin>
				<ymin>25</ymin>
				<xmax>325</xmax>
				<ymax>72</ymax>
			</bndbox>
		</object>
		<object>
			<name>pedestrian</name>
			<pose>Unspecified</pose>
			<truncated>0</truncated>
			<difficult>0</difficult>
			<bndbox>
				<xmin>170</xmin>
				<ymin>88</ymin>
				<xmax>189</xmax>
				<ymax>129</ymax>
			</bndbox>
		</object>
		<object>
			<name>pedestrian</name>
			<pose>Unspecified</pose>
			<truncated>0</truncated>
			<difficult>0</difficult>
			<bndbox>
				<xmin>226</xmin>
				<ymin>113</ymin>
				<xmax>246</xmax>
				<ymax>151</ymax>
			</bndbox>
		</object>
		<object>
			<name>pedestrian</name>
			<pose>Unspecified</pose>
			<truncated>0</truncated>
			<difficult>0</difficult>
			<bndbox>
				<xmin>214</xmin>
				<ymin>108</ymin>
				<xmax>228</xmax>
				<ymax>145</ymax>
			</bndbox>
		</object>
		<object>
			<name>pedestrian</name>
			<pose>Unspecified</pose>
			<truncated>0</truncated>
			<difficult>0</difficult>
			<bndbox>
				<xmin>208</xmin>
				<ymin>120</ymin>
				<xmax>218</xmax>
				<ymax>148</ymax>
			</bndbox>
		</object>
		<object>
			<name>pedestrian</name>
			<pose>Unspecified</pose>
			<truncated>0</truncated>
			<difficult>0</difficult>
			<bndbox>
				<xmin>204</xmin>
				<ymin>116</ymin>
				<xmax>215</xmax>
				<ymax>142</ymax>
			</bndbox>
		</object>
		<object>
			<name>pedestrian</name>
			<pose>Unspecified</pose>
			<truncated>0</truncated>
			<difficult>0</difficult>
			<bndbox>
				<xmin>249</xmin>
				<ymin>161</ymin>
				<xmax>264</xmax>
				<ymax>198</ymax>
			</bndbox>
		</object>
		<object>
			<name>pedestrian</name>
			<pose>Unspecified</pose>
			<truncated>0</truncated>
			<difficult>0</difficult>
			<bndbox>
				<xmin>261</xmin>
				<ymin>154</ymin>
				<xmax>278</xmax>
				<ymax>197</ymax>
			</bndbox>
		</object>
		<object>
			<name>pedestrian</name>
			<pose>Unspecified</pose>
			<truncated>0</truncated>
			<difficult>0</difficult>
			<bndbox>
				<xmin>346</xmin>
				<ymin>141</ymin>
				<xmax>367</xmax>
				<ymax>184</ymax>
			</bndbox>
		</object>
		<object>
			<name>pedestrian</name>
			<pose>Unspecified</pose>
			<truncated>0</truncated>
			<difficult>0</difficult>
			<bndbox>
				<xmin>348</xmin>
				<ymin>160</ymin>
				<xmax>358</xmax>
				<ymax>192</ymax>
			</bndbox>
		</object>
		<object>
			<name>bicycle</name>
			<pose>Unspecified</pose>
			<truncated>0</truncated>
			<difficult>0</difficult>
			<bndbox>
				<xmin>300</xmin>
				<ymin>237</ymin>
				<xmax>324</xmax>
				<ymax>273</ymax>
			</bndbox>
		</object>
		<object>
			<name>pedestrian</name>
			<pose>Unspecified</pose>
			<truncated>0</truncated>
			<difficult>0</difficult>
			<bndbox>
				<xmin>314</xmin>
				<ymin>206</ymin>
				<xmax>331</xmax>
				<ymax>247</ymax>
			</bndbox>
		</object>
		<object>
			<name>pedestrian</name>
			<pose>Unspecified</pose>
			<truncated>0</truncated>
			<difficult>0</difficult>
			<bndbox>
				<xmin>323</xmin>
				<ymin>218</ymin>
				<xmax>342</xmax>
				<ymax>259</ymax>
			</bndbox>
		</object>
		<object>
			<name>pedestrian</name>
			<pose>Unspecified</pose>
			<truncated>0</truncated>
			<difficult>0</difficult>
			<bndbox>
				<xmin>336</xmin>
				<ymin>198</ymin>
				<xmax>352</xmax>
				<ymax>241</ymax>
			</bndbox>
		</object>
		<object>
			<name>pedestrian</name>
			<pose>Unspecified</pose>
			<truncated>0</truncated>
			<difficult>0</difficult>
			<bndbox>
				<xmin>351</xmin>
				<ymin>217</ymin>
				<xmax>368</xmax>
				<ymax>263</ymax>
			</bndbox>
		</object>
		<object>
			<name>pedestrian</name>
			<pose>Unspecified</pose>
			<truncated>0</truncated>
			<difficult>0</difficult>
			<bndbox>
				<xmin>346</xmin>
				<ymin>183</ymin>
				<xmax>361</xmax>
				<ymax>229</ymax>
			</bndbox>
		</object>
		<object>
			<name>motor</name>
			<pose>Unspecified</pose>
			<truncated>0</truncated>
			<difficult>0</difficult>
			<bndbox>
				<xmin>329</xmin>
				<ymin>190</ymin>
				<xmax>365</xmax>
				<ymax>219</ymax>
			</bndbox>
		</object>
		<object>
			<name>pedestrian</name>
			<pose>Unspecified</pose>
			<truncated>0</truncated>
			<difficult>0</difficult>
			<bndbox>
				<xmin>362</xmin>
				<ymin>184</ymin>
				<xmax>376</xmax>
				<ymax>222</ymax>
			</bndbox>
		</object>
		<object>
			<name>pedestrian</name>
			<pose>Unspecified</pose>
			<truncated>0</truncated>
			<difficult>0</difficult>
			<bndbox>
				<xmin>364</xmin>
				<ymin>206</ymin>
				<xmax>381</xmax>
				<ymax>251</ymax>
			</bndbox>
		</object>
		<object>
			<name>pedestrian</name>
			<pose>Unspecified</pose>
			<truncated>0</truncated>
			<difficult>0</difficult>
			<bndbox>
				<xmin>375</xmin>
				<ymin>203</ymin>
				<xmax>388</xmax>
				<ymax>246</ymax>
			</bndbox>
		</object>
		<object>
			<name>pedestrian</name>
			<pose>Unspecified</pose>
			<truncated>0</truncated>
			<difficult>0</difficult>
			<bndbox>
				<xmin>377</xmin>
				<ymin>191</ymin>
				<xmax>388</xmax>
				<ymax>228</ymax>
			</bndbox>
		</object>
		<object>
			<name>pedestrian</name>
			<pose>Unspecified</pose>
			<truncated>0</truncated>
			<difficult>0</difficult>
			<bndbox>
				<xmin>449</xmin>
				<ymin>128</ymin>
				<xmax>462</xmax>
				<ymax>167</ymax>
			</bndbox>
		</object>
		<object>
			<name>pedestrian</name>
			<pose>Unspecified</pose>
			<truncated>0</truncated>
			<difficult>0</difficult>
			<bndbox>
				<xmin>452</xmin>
				<ymin>179</ymin>
				<xmax>462</xmax>
				<ymax>210</ymax>
			</bndbox>
		</object>
		<object>
			<name>pedestrian</name>
			<pose>Unspecified</pose>
			<truncated>0</truncated>
			<difficult>0</difficult>
			<bndbox>
				<xmin>461</xmin>
				<ymin>189</ymin>
				<xmax>482</xmax>
				<ymax>235</ymax>
			</bndbox>
		</object>
		<object>
			<name>pedestrian</name>
			<pose>Unspecified</pose>
			<truncated>0</truncated>
			<difficult>0</difficult>
			<bndbox>
				<xmin>468</xmin>
				<ymin>179</ymin>
				<xmax>482</xmax>
				<ymax>214</ymax>
			</bndbox>
		</object>
		<object>
			<name>pedestrian</name>
			<pose>Unspecified</pose>
			<truncated>0</truncated>
			<difficult>0</difficult>
			<bndbox>
				<xmin>461</xmin>
				<ymin>163</ymin>
				<xmax>478</xmax>
				<ymax>201</ymax>
			</bndbox>
		</object>
		<object>
			<name>pedestrian</name>
			<pose>Unspecified</pose>
			<truncated>0</truncated>
			<difficult>0</difficult>
			<bndbox>
				<xmin>470</xmin>
				<ymin>137</ymin>
				<xmax>482</xmax>
				<ymax>172</ymax>
			</bndbox>
		</object>
		<object>
			<name>pedestrian</name>
			<pose>Unspecified</pose>
			<truncated>0</truncated>
			<difficult>0</difficult>
			<bndbox>
				<xmin>476</xmin>
				<ymin>125</ymin>
				<xmax>487</xmax>
				<ymax>158</ymax>
			</bndbox>
		</object>
		<object>
			<name>pedestrian</name>
			<pose>Unspecified</pose>
			<truncated>0</truncated>
			<difficult>0</difficult>
			<bndbox>
				<xmin>481</xmin>
				<ymin>146</ymin>
				<xmax>494</xmax>
				<ymax>185</ymax>
			</bndbox>
		</object>
		<object>
			<name>pedestrian</name>
			<pose>Unspecified</pose>
			<truncated>0</truncated>
			<difficult>0</difficult>
			<bndbox>
				<xmin>485</xmin>
				<ymin>129</ymin>
				<xmax>497</xmax>
				<ymax>161</ymax>
			</bndbox>
		</object>
		<object>
			<name>pedestrian</name>
			<pose>Unspecified</pose>
			<truncated>0</truncated>
			<difficult>0</difficult>
			<bndbox>
				<xmin>491</xmin>
				<ymin>144</ymin>
				<xmax>500</xmax>
				<ymax>177</ymax>
			</bndbox>
		</object>
		<object>
			<name>pedestrian</name>
			<pose>Unspecified</pose>
			<truncated>0</truncated>
			<difficult>0</difficult>
			<bndbox>
				<xmin>494</xmin>
				<ymin>136</ymin>
				<xmax>503</xmax>
				<ymax>164</ymax>
			</bndbox>
		</object>
		<object>
			<name>pedestrian</name>
			<pose>Unspecified</pose>
			<truncated>0</truncated>
			<difficult>0</difficult>
			<bndbox>
				<xmin>498</xmin>
				<ymin>126</ymin>
				<xmax>510</xmax>
				<ymax>164</ymax>
			</bndbox>
		</object>
		<object>
			<name>pedestrian</name>
			<pose>Unspecified</pose>
			<truncated>0</truncated>
			<difficult>0</difficult>
			<bndbox>
				<xmin>551</xmin>
				<ymin>124</ymin>
				<xmax>567</xmax>
				<ymax>166</ymax>
			</bndbox>
		</object>
		<object>
			<name>bicycle</name>
			<pose>Unspecified</pose>
			<truncated>0</truncated>
			<difficult>0</difficult>
			<bndbox>
				<xmin>289</xmin>
				<ymin>250</ymin>
				<xmax>310</xmax>
				<ymax>293</ymax>
			</bndbox>
		</object>
		<object>
			<name>bicycle</name>
			<pose>Unspecified</pose>
			<truncated>0</truncated>
			<difficult>0</difficult>
			<bndbox>
				<xmin>269</xmin>
				<ymin>291</ymin>
				<xmax>301</xmax>
				<ymax>337</ymax>
			</bndbox>
		</object>
		<object>
			<name>tricycle</name>
			<pose>Unspecified</pose>
			<truncated>0</truncated>
			<difficult>0</difficult>
			<bndbox>
				<xmin>251</xmin>
				<ymin>323</ymin>
				<xmax>335</xmax>
				<ymax>407</ymax>
			</bndbox>
		</object>
		<object>
			<name>people</name>
			<pose>Unspecified</pose>
			<truncated>0</truncated>
			<difficult>0</difficult>
			<bndbox>
				<xmin>322</xmin>
				<ymin>285</ymin>
				<xmax>342</xmax>
				<ymax>316</ymax>
			</bndbox>
		</object>
		<object>
			<name>pedestrian</name>
			<pose>Unspecified</pose>
			<truncated>0</truncated>
			<difficult>0</difficult>
			<bndbox>
				<xmin>422</xmin>
				<ymin>296</ymin>
				<xmax>448</xmax>
				<ymax>354</ymax>
			</bndbox>
		</object>
		<object>
			<name>pedestrian</name>
			<pose>Unspecified</pose>
			<truncated>0</truncated>
			<difficult>0</difficult>
			<bndbox>
				<xmin>443</xmin>
				<ymin>301</ymin>
				<xmax>464</xmax>
				<ymax>345</ymax>
			</bndbox>
		</object>
		<object>
			<name>people</name>
			<pose>Unspecified</pose>
			<truncated>0</truncated>
			<difficult>0</difficult>
			<bndbox>
				<xmin>383</xmin>
				<ymin>383</ymin>
				<xmax>408</xmax>
				<ymax>420</ymax>
			</bndbox>
		</object>
		<object>
			<name>people</name>
			<pose>Unspecified</pose>
			<truncated>0</truncated>
			<difficult>0</difficult>
			<bndbox>
				<xmin>409</xmin>
				<ymin>378</ymin>
				<xmax>423</xmax>
				<ymax>400</ymax>
			</bndbox>
		</object>
		<object>
			<name>people</name>
			<pose>Unspecified</pose>
			<truncated>0</truncated>
			<difficult>0</difficult>
			<bndbox>
				<xmin>417</xmin>
				<ymin>375</ymin>
				<xmax>444</xmax>
				<ymax>408</ymax>
			</bndbox>
		</object>
		<object>
			<name>pedestrian</name>
			<pose>Unspecified</pose>
			<truncated>0</truncated>
			<difficult>0</difficult>
			<bndbox>
				<xmin>429</xmin>
				<ymin>389</ymin>
				<xmax>446</xmax>
				<ymax>417</ymax>
			</bndbox>
		</object>
		<object>
			<name>motor</name>
			<pose>Unspecified</pose>
			<truncated>0</truncated>
			<difficult>0</difficult>
			<bndbox>
				<xmin>370</xmin>
				<ymin>497</ymin>
				<xmax>452</xmax>
				<ymax>547</ymax>
			</bndbox>
		</object>
		<object>
			<name>pedestrian</name>
			<pose>Unspecified</pose>
			<truncated>0</truncated>
			<difficult>0</difficult>
			<bndbox>
				<xmin>520</xmin>
				<ymin>465</ymin>
				<xmax>548</xmax>
				<ymax>528</ymax>
			</bndbox>
		</object>
		<object>
			<name>pedestrian</name>
			<pose>Unspecified</pose>
			<truncated>0</truncated>
			<difficult>0</difficult>
			<bndbox>
				<xmin>539</xmin>
				<ymin>452</ymin>
				<xmax>560</xmax>
				<ymax>510</ymax>
			</bndbox>
		</object>
		<object>
			<name>pedestrian</name>
			<pose>Unspecified</pose>
			<truncated>0</truncated>
			<difficult>0</difficult>
			<bndbox>
				<xmin>546</xmin>
				<ymin>483</ymin>
				<xmax>570</xmax>
				<ymax>540</ymax>
			</bndbox>
		</object>
		<object>
			<name>people</name>
			<pose>Unspecified</pose>
			<truncated>0</truncated>
			<difficult>0</difficult>
			<bndbox>
				<xmin>553</xmin>
				<ymin>479</ymin>
				<xmax>565</xmax>
				<ymax>504</ymax>
			</bndbox>
		</object>
		<object>
			<name>pedestrian</name>
			<pose>Unspecified</pose>
			<truncated>0</truncated>
			<difficult>0</difficult>
			<bndbox>
				<xmin>595</xmin>
				<ymin>173</ymin>
				<xmax>609</xmax>
				<ymax>215</ymax>
			</bndbox>
		</object>
		<object>
			<name>pedestrian</name>
			<pose>Unspecified</pose>
			<truncated>0</truncated>
			<difficult>0</difficult>
			<bndbox>
				<xmin>609</xmin>
				<ymin>162</ymin>
				<xmax>624</xmax>
				<ymax>207</ymax>
			</bndbox>
		</object>
		<object>
			<name>pedestrian</name>
			<pose>Unspecified</pose>
			<truncated>0</truncated>
			<difficult>0</difficult>
			<bndbox>
				<xmin>605</xmin>
				<ymin>196</ymin>
				<xmax>619</xmax>
				<ymax>243</ymax>
			</bndbox>
		</object>
		<object>
			<name>pedestrian</name>
			<pose>Unspecified</pose>
			<truncated>0</truncated>
			<difficult>0</difficult>
			<bndbox>
				<xmin>573</xmin>
				<ymin>204</ymin>
				<xmax>590</xmax>
				<ymax>245</ymax>
			</bndbox>
		</object>
		<object>
			<name>people</name>
			<pose>Unspecified</pose>
			<truncated>0</truncated>
			<difficult>0</difficult>
			<bndbox>
				<xmin>579</xmin>
				<ymin>209</ymin>
				<xmax>593</xmax>
				<ymax>233</ymax>
			</bndbox>
		</object>
		<object>
			<name>pedestrian</name>
			<pose>Unspecified</pose>
			<truncated>0</truncated>
			<difficult>0</difficult>
			<bndbox>
				<xmin>478</xmin>
				<ymin>288</ymin>
				<xmax>497</xmax>
				<ymax>339</ymax>
			</bndbox>
		</object>
		<object>
			<name>pedestrian</name>
			<pose>Unspecified</pose>
			<truncated>0</truncated>
			<difficult>0</difficult>
			<bndbox>
				<xmin>495</xmin>
				<ymin>286</ymin>
				<xmax>516</xmax>
				<ymax>334</ymax>
			</bndbox>
		</object>
		<object>
			<name>pedestrian</name>
			<pose>Unspecified</pose>
			<truncated>0</truncated>
			<difficult>0</difficult>
			<bndbox>
				<xmin>590</xmin>
				<ymin>373</ymin>
				<xmax>610</xmax>
				<ymax>435</ymax>
			</bndbox>
		</object>
		<object>
			<name>pedestrian</name>
			<pose>Unspecified</pose>
			<truncated>0</truncated>
			<difficult>0</difficult>
			<bndbox>
				<xmin>594</xmin>
				<ymin>296</ymin>
				<xmax>615</xmax>
				<ymax>334</ymax>
			</bndbox>
		</object>
		<object>
			<name>pedestrian</name>
			<pose>Unspecified</pose>
			<truncated>0</truncated>
			<difficult>0</difficult>
			<bndbox>
				<xmin>582</xmin>
				<ymin>301</ymin>
				<xmax>596</xmax>
				<ymax>346</ymax>
			</bndbox>
		</object>
		<object>
			<name>pedestrian</name>
			<pose>Unspecified</pose>
			<truncated>0</truncated>
			<difficult>0</difficult>
			<bndbox>
				<xmin>586</xmin>
				<ymin>313</ymin>
				<xmax>603</xmax>
				<ymax>359</ymax>
			</bndbox>
		</object>
		<object>
			<name>pedestrian</name>
			<pose>Unspecified</pose>
			<truncated>0</truncated>
			<difficult>0</difficult>
			<bndbox>
				<xmin>608</xmin>
				<ymin>315</ymin>
				<xmax>626</xmax>
				<ymax>357</ymax>
			</bndbox>
		</object>
		<object>
			<name>pedestrian</name>
			<pose>Unspecified</pose>
			<truncated>0</truncated>
			<difficult>0</difficult>
			<bndbox>
				<xmin>628</xmin>
				<ymin>360</ymin>
				<xmax>644</xmax>
				<ymax>403</ymax>
			</bndbox>
		</object>
		<object>
			<name>pedestrian</name>
			<pose>Unspecified</pose>
			<truncated>0</truncated>
			<difficult>0</difficult>
			<bndbox>
				<xmin>654</xmin>
				<ymin>411</ymin>
				<xmax>672</xmax>
				<ymax>458</ymax>
			</bndbox>
		</object>
		<object>
			<name>pedestrian</name>
			<pose>Unspecified</pose>
			<truncated>0</truncated>
			<difficult>0</difficult>
			<bndbox>
				<xmin>650</xmin>
				<ymin>370</ymin>
				<xmax>670</xmax>
				<ymax>423</ymax>
			</bndbox>
		</object>
		<object>
			<name>people</name>
			<pose>Unspecified</pose>
			<truncated>0</truncated>
			<difficult>0</difficult>
			<bndbox>
				<xmin>533</xmin>
				<ymin>607</ymin>
				<xmax>571</xmax>
				<ymax>676</ymax>
			</bndbox>
		</object>
		<object>
			<name>bicycle</name>
			<pose>Unspecified</pose>
			<truncated>0</truncated>
			<difficult>0</difficult>
			<bndbox>
				<xmin>524</xmin>
				<ymin>623</ymin>
				<xmax>585</xmax>
				<ymax>678</ymax>
			</bndbox>
		</object>
		<object>
			<name>pedestrian</name>
			<pose>Unspecified</pose>
			<truncated>0</truncated>
			<difficult>0</difficult>
			<bndbox>
				<xmin>708</xmin>
				<ymin>356</ymin>
				<xmax>733</xmax>
				<ymax>412</ymax>
			</bndbox>
		</object>
		<object>
			<name>pedestrian</name>
			<pose>Unspecified</pose>
			<truncated>0</truncated>
			<difficult>0</difficult>
			<bndbox>
				<xmin>767</xmin>
				<ymin>224</ymin>
				<xmax>783</xmax>
				<ymax>271</ymax>
			</bndbox>
		</object>
		<object>
			<name>pedestrian</name>
			<pose>Unspecified</pose>
			<truncated>0</truncated>
			<difficult>0</difficult>
			<bndbox>
				<xmin>781</xmin>
				<ymin>226</ymin>
				<xmax>798</xmax>
				<ymax>272</ymax>
			</bndbox>
		</object>
		<object>
			<name>tricycle</name>
			<pose>Unspecified</pose>
			<truncated>0</truncated>
			<difficult>0</difficult>
			<bndbox>
				<xmin>749</xmin>
				<ymin>214</ymin>
				<xmax>817</xmax>
				<ymax>271</ymax>
			</bndbox>
		</object>
		<object>
			<name>pedestrian</name>
			<pose>Unspecified</pose>
			<truncated>0</truncated>
			<difficult>0</difficult>
			<bndbox>
				<xmin>780</xmin>
				<ymin>257</ymin>
				<xmax>797</xmax>
				<ymax>301</ymax>
			</bndbox>
		</object>
		<object>
			<name>pedestrian</name>
			<pose>Unspecified</pose>
			<truncated>0</truncated>
			<difficult>0</difficult>
			<bndbox>
				<xmin>772</xmin>
				<ymin>267</ymin>
				<xmax>784</xmax>
				<ymax>307</ymax>
			</bndbox>
		</object>
		<object>
			<name>pedestrian</name>
			<pose>Unspecified</pose>
			<truncated>0</truncated>
			<difficult>0</difficult>
			<bndbox>
				<xmin>796</xmin>
				<ymin>288</ymin>
				<xmax>819</xmax>
				<ymax>336</ymax>
			</bndbox>
		</object>
		<object>
			<name>pedestrian</name>
			<pose>Unspecified</pose>
			<truncated>0</truncated>
			<difficult>0</difficult>
			<bndbox>
				<xmin>822</xmin>
				<ymin>361</ymin>
				<xmax>836</xmax>
				<ymax>393</ymax>
			</bndbox>
		</object>
		<object>
			<name>pedestrian</name>
			<pose>Unspecified</pose>
			<truncated>0</truncated>
			<difficult>0</difficult>
			<bndbox>
				<xmin>869</xmin>
				<ymin>341</ymin>
				<xmax>888</xmax>
				<ymax>390</ymax>
			</bndbox>
		</object>
		<object>
			<name>pedestrian</name>
			<pose>Unspecified</pose>
			<truncated>0</truncated>
			<difficult>0</difficult>
			<bndbox>
				<xmin>871</xmin>
				<ymin>350</ymin>
				<xmax>889</xmax>
				<ymax>402</ymax>
			</bndbox>
		</object>
		<object>
			<name>pedestrian</name>
			<pose>Unspecified</pose>
			<truncated>0</truncated>
			<difficult>0</difficult>
			<bndbox>
				<xmin>863</xmin>
				<ymin>264</ymin>
				<xmax>881</xmax>
				<ymax>301</ymax>
			</bndbox>
		</object>
		<object>
			<name>pedestrian</name>
			<pose>Unspecified</pose>
			<truncated>0</truncated>
			<difficult>0</difficult>
			<bndbox>
				<xmin>876</xmin>
				<ymin>254</ymin>
				<xmax>896</xmax>
				<ymax>304</ymax>
			</bndbox>
		</object>
		<object>
			<name>pedestrian</name>
			<pose>Unspecified</pose>
			<truncated>0</truncated>
			<difficult>0</difficult>
			<bndbox>
				<xmin>866</xmin>
				<ymin>290</ymin>
				<xmax>885</xmax>
				<ymax>342</ymax>
			</bndbox>
		</object>
		<object>
			<name>pedestrian</name>
			<pose>Unspecified</pose>
			<truncated>0</truncated>
			<difficult>0</difficult>
			<bndbox>
				<xmin>912</xmin>
				<ymin>253</ymin>
				<xmax>929</xmax>
				<ymax>300</ymax>
			</bndbox>
		</object>
		<object>
			<name>pedestrian</name>
			<pose>Unspecified</pose>
			<truncated>0</truncated>
			<difficult>0</difficult>
			<bndbox>
				<xmin>895</xmin>
				<ymin>288</ymin>
				<xmax>912</xmax>
				<ymax>339</ymax>
			</bndbox>
		</object>
		<object>
			<name>pedestrian</name>
			<pose>Unspecified</pose>
			<truncated>0</truncated>
			<difficult>0</difficult>
			<bndbox>
				<xmin>904</xmin>
				<ymin>292</ymin>
				<xmax>917</xmax>
				<ymax>322</ymax>
			</bndbox>
		</object>
		<object>
			<name>pedestrian</name>
			<pose>Unspecified</pose>
			<truncated>0</truncated>
			<difficult>0</difficult>
			<bndbox>
				<xmin>913</xmin>
				<ymin>282</ymin>
				<xmax>933</xmax>
				<ymax>330</ymax>
			</bndbox>
		</object>
		<object>
			<name>bicycle</name>
			<pose>Unspecified</pose>
			<truncated>0</truncated>
			<difficult>0</difficult>
			<bndbox>
				<xmin>897</xmin>
				<ymin>311</ymin>
				<xmax>917</xmax>
				<ymax>344</ymax>
			</bndbox>
		</object>
		<object>
			<name>pedestrian</name>
			<pose>Unspecified</pose>
			<truncated>0</truncated>
			<difficult>0</difficult>
			<bndbox>
				<xmin>923</xmin>
				<ymin>357</ymin>
				<xmax>946</xmax>
				<ymax>423</ymax>
			</bndbox>
		</object>
		<object>
			<name>pedestrian</name>
			<pose>Unspecified</pose>
			<truncated>0</truncated>
			<difficult>0</difficult>
			<bndbox>
				<xmin>971</xmin>
				<ymin>231</ymin>
				<xmax>994</xmax>
				<ymax>279</ymax>
			</bndbox>
		</object>
		<object>
			<name>pedestrian</name>
			<pose>Unspecified</pose>
			<truncated>0</truncated>
			<difficult>0</difficult>
			<bndbox>
				<xmin>962</xmin>
				<ymin>331</ymin>
				<xmax>983</xmax>
				<ymax>386</ymax>
			</bndbox>
		</object>
		<object>
			<name>pedestrian</name>
			<pose>Unspecified</pose>
			<truncated>0</truncated>
			<difficult>0</difficult>
			<bndbox>
				<xmin>980</xmin>
				<ymin>338</ymin>
				<xmax>995</xmax>
				<ymax>362</ymax>
			</bndbox>
		</object>
		<object>
			<name>pedestrian</name>
			<pose>Unspecified</pose>
			<truncated>0</truncated>
			<difficult>0</difficult>
			<bndbox>
				<xmin>979</xmin>
				<ymin>336</ymin>
				<xmax>1002</xmax>
				<ymax>389</ymax>
			</bndbox>
		</object>
		<object>
			<name>pedestrian</name>
			<pose>Unspecified</pose>
			<truncated>0</truncated>
			<difficult>0</difficult>
			<bndbox>
				<xmin>985</xmin>
				<ymin>326</ymin>
				<xmax>1013</xmax>
				<ymax>379</ymax>
			</bndbox>
		</object>
		<object>
			<name>pedestrian</name>
			<pose>Unspecified</pose>
			<truncated>0</truncated>
			<difficult>0</difficult>
			<bndbox>
				<xmin>1007</xmin>
				<ymin>317</ymin>
				<xmax>1030</xmax>
				<ymax>345</ymax>
			</bndbox>
		</object>
		<object>
			<name>pedestrian</name>
			<pose>Unspecified</pose>
			<truncated>0</truncated>
			<difficult>0</difficult>
			<bndbox>
				<xmin>1015</xmin>
				<ymin>322</ymin>
				<xmax>1039</xmax>
				<ymax>380</ymax>
			</bndbox>
		</object>
		<object>
			<name>pedestrian</name>
			<pose>Unspecified</pose>
			<truncated>0</truncated>
			<difficult>0</difficult>
			<bndbox>
				<xmin>1036</xmin>
				<ymin>315</ymin>
				<xmax>1060</xmax>
				<ymax>369</ymax>
			</bndbox>
		</object>
		<object>
			<name>people</name>
			<pose>Unspecified</pose>
			<truncated>0</truncated>
			<difficult>0</difficult>
			<bndbox>
				<xmin>1049</xmin>
				<ymin>313</ymin>
				<xmax>1061</xmax>
				<ymax>339</ymax>
			</bndbox>
		</object>
		<object>
			<name>pedestrian</name>
			<pose>Unspecified</pose>
			<truncated>0</truncated>
			<difficult>0</difficult>
			<bndbox>
				<xmin>1068</xmin>
				<ymin>331</ymin>
				<xmax>1092</xmax>
				<ymax>367</ymax>
			</bndbox>
		</object>
		<object>
			<name>pedestrian</name>
			<pose>Unspecified</pose>
			<truncated>0</truncated>
			<difficult>0</difficult>
			<bndbox>
				<xmin>1089</xmin>
				<ymin>325</ymin>
				<xmax>1119</xmax>
				<ymax>377</ymax>
			</bndbox>
		</object>
		<object>
			<name>pedestrian</name>
			<pose>Unspecified</pose>
			<truncated>0</truncated>
			<difficult>0</difficult>
			<bndbox>
				<xmin>1104</xmin>
				<ymin>331</ymin>
				<xmax>1134</xmax>
				<ymax>380</ymax>
			</bndbox>
		</object>
		<object>
			<name>pedestrian</name>
			<pose>Unspecified</pose>
			<truncated>0</truncated>
			<difficult>0</difficult>
			<bndbox>
				<xmin>1094</xmin>
				<ymin>361</ymin>
				<xmax>1119</xmax>
				<ymax>413</ymax>
			</bndbox>
		</object>
		<object>
			<name>pedestrian</name>
			<pose>Unspecified</pose>
			<truncated>0</truncated>
			<difficult>0</difficult>
			<bndbox>
				<xmin>1121</xmin>
				<ymin>367</ymin>
				<xmax>1142</xmax>
				<ymax>394</ymax>
			</bndbox>
		</object>
		<object>
			<name>pedestrian</name>
			<pose>Unspecified</pose>
			<truncated>0</truncated>
			<difficult>0</difficult>
			<bndbox>
				<xmin>1157</xmin>
				<ymin>357</ymin>
				<xmax>1184</xmax>
				<ymax>413</ymax>
			</bndbox>
		</object>
		<object>
			<name>pedestrian</name>
			<pose>Unspecified</pose>
			<truncated>0</truncated>
			<difficult>0</difficult>
			<bndbox>
				<xmin>936</xmin>
				<ymin>583</ymin>
				<xmax>968</xmax>
				<ymax>648</ymax>
			</bndbox>
		</object>
		<object>
			<name>pedestrian</name>
			<pose>Unspecified</pose>
			<truncated>0</truncated>
			<difficult>0</difficult>
			<bndbox>
				<xmin>960</xmin>
				<ymin>565</ymin>
				<xmax>990</xmax>
				<ymax>632</ymax>
			</bndbox>
		</object>
		<object>
			<name>people</name>
			<pose>Unspecified</pose>
			<truncated>0</truncated>
			<difficult>0</difficult>
			<bndbox>
				<xmin>1276</xmin>
				<ymin>445</ymin>
				<xmax>1313</xmax>
				<ymax>497</ymax>
			</bndbox>
		</object>
		<object>
			<name>van</name>
			<pose>Unspecified</pose>
			<truncated>0</truncated>
			<difficult>0</difficult>
			<bndbox>
				<xmin>687</xmin>
				<ymin>74</ymin>
				<xmax>766</xmax>
				<ymax>123</ymax>
			</bndbox>
		</object>
		<object>
			<name>car</name>
			<pose>Unspecified</pose>
			<truncated>0</truncated>
			<difficult>0</difficult>
			<bndbox>
				<xmin>770</xmin>
				<ymin>57</ymin>
				<xmax>851</xmax>
				<ymax>94</ymax>
			</bndbox>
		</object>
		<object>
			<name>car</name>
			<pose>Unspecified</pose>
			<truncated>0</truncated>
			<difficult>0</difficult>
			<bndbox>
				<xmin>859</xmin>
				<ymin>45</ymin>
				<xmax>915</xmax>
				<ymax>82</ymax>
			</bndbox>
		</object>
		<object>
			<name>car</name>
			<pose>Unspecified</pose>
			<truncated>0</truncated>
			<difficult>0</difficult>
			<bndbox>
				<xmin>913</xmin>
				<ymin>36</ymin>
				<xmax>961</xmax>
				<ymax>69</ymax>
			</bndbox>
		</object>
		<object>
			<name>car</name>
			<pose>Unspecified</pose>
			<truncated>0</truncated>
			<difficult>0</difficult>
			<bndbox>
				<xmin>947</xmin>
				<ymin>24</ymin>
				<xmax>1010</xmax>
				<ymax>58</ymax>
			</bndbox>
		</object>
		<object>
			<name>car</name>
			<pose>Unspecified</pose>
			<truncated>0</truncated>
			<difficult>0</difficult>
			<bndbox>
				<xmin>1023</xmin>
				<ymin>11</ymin>
				<xmax>1081</xmax>
				<ymax>42</ymax>
			</bndbox>
		</object>
		<object>
			<name>car</name>
			<pose>Unspecified</pose>
			<truncated>0</truncated>
			<difficult>0</difficult>
			<bndbox>
				<xmin>426</xmin>
				<ymin>1</ymin>
				<xmax>504</xmax>
				<ymax>32</ymax>
			</bndbox>
		</object>
	</annotation>
