<?xml version="1.0" encoding="utf-8"?>
	<annotation>
		<folder>driving_annotation_dataset</folder>
		<filename>0000205_00000_d_0000196.jpg</filename>
		<size>
			<width>960</width>
			<height>540</height>
			<depth>3</depth>
		</size>
		<object>
			<name>car</name>
			<pose>Unspecified</pose>
			<truncated>0</truncated>
			<difficult>0</difficult>
			<bndbox>
				<xmin>57</xmin>
				<ymin>429</ymin>
				<xmax>174</xmax>
				<ymax>514</ymax>
			</bndbox>
		</object>
		<object>
			<name>car</name>
			<pose>Unspecified</pose>
			<truncated>0</truncated>
			<difficult>0</difficult>
			<bndbox>
				<xmin>284</xmin>
				<ymin>149</ymin>
				<xmax>326</xmax>
				<ymax>226</ymax>
			</bndbox>
		</object>
		<object>
			<name>car</name>
			<pose>Unspecified</pose>
			<truncated>0</truncated>
			<difficult>0</difficult>
			<bndbox>
				<xmin>571</xmin>
				<ymin>336</ymin>
				<xmax>615</xmax>
				<ymax>414</ymax>
			</bndbox>
		</object>
		<object>
			<name>car</name>
			<pose>Unspecified</pose>
			<truncated>0</truncated>
			<difficult>0</difficult>
			<bndbox>
				<xmin>646</xmin>
				<ymin>14</ymin>
				<xmax>682</xmax>
				<ymax>61</ymax>
			</bndbox>
		</object>
		<object>
			<name>car</name>
			<pose>Unspecified</pose>
			<truncated>0</truncated>
			<difficult>0</difficult>
			<bndbox>
				<xmin>690</xmin>
				<ymin>6</ymin>
				<xmax>734</xmax>
				<ymax>59</ymax>
			</bndbox>
		</object>
		<object>
			<name>car</name>
			<pose>Unspecified</pose>
			<truncated>0</truncated>
			<difficult>0</difficult>
			<bndbox>
				<xmin>738</xmin>
				<ymin>12</ymin>
				<xmax>777</xmax>
				<ymax>62</ymax>
			</bndbox>
		</object>
		<object>
			<name>car</name>
			<pose>Unspecified</pose>
			<truncated>0</truncated>
			<difficult>0</difficult>
			<bndbox>
				<xmin>655</xmin>
				<ymin>342</ymin>
				<xmax>724</xmax>
				<ymax>395</ymax>
			</bndbox>
		</object>
		<object>
			<name>tricycle</name>
			<pose>Unspecified</pose>
			<truncated>0</truncated>
			<difficult>0</difficult>
			<bndbox>
				<xmin>784</xmin>
				<ymin>159</ymin>
				<xmax>814</xmax>
				<ymax>211</ymax>
			</bndbox>
		</object>
		<object>
			<name>tricycle</name>
			<pose>Unspecified</pose>
			<truncated>0</truncated>
			<difficult>0</difficult>
			<bndbox>
				<xmin>506</xmin>
				<ymin>197</ymin>
				<xmax>529</xmax>
				<ymax>248</ymax>
			</bndbox>
		</object>
		<object>
			<name>tricycle</name>
			<pose>Unspecified</pose>
			<truncated>0</truncated>
			<difficult>0</difficult>
			<bndbox>
				<xmin>207</xmin>
				<ymin>415</ymin>
				<xmax>259</xmax>
				<ymax>521</ymax>
			</bndbox>
		</object>
		<object>
			<name>tricycle</name>
			<pose>Unspecified</pose>
			<truncated>0</truncated>
			<difficult>0</difficult>
			<bndbox>
				<xmin>1</xmin>
				<ymin>350</ymin>
				<xmax>51</xmax>
				<ymax>380</ymax>
			</bndbox>
		</object>
		<object>
			<name>pedestrian</name>
			<pose>Unspecified</pose>
			<truncated>0</truncated>
			<difficult>0</difficult>
			<bndbox>
				<xmin>107</xmin>
				<ymin>260</ymin>
				<xmax>130</xmax>
				<ymax>287</ymax>
			</bndbox>
		</object>
		<object>
			<name>tricycle</name>
			<pose>Unspecified</pose>
			<truncated>0</truncated>
			<difficult>0</difficult>
			<bndbox>
				<xmin>552</xmin>
				<ymin>0</ymin>
				<xmax>580</xmax>
				<ymax>36</ymax>
			</bndbox>
		</object>
		<object>
			<name>car</name>
			<pose>Unspecified</pose>
			<truncated>0</truncated>
			<difficult>0</difficult>
			<bndbox>
				<xmin>319</xmin>
				<ymin>2</ymin>
				<xmax>350</xmax>
				<ymax>29</ymax>
			</bndbox>
		</object>
		<object>
			<name>pedestrian</name>
			<pose>Unspecified</pose>
			<truncated>0</truncated>
			<difficult>0</difficult>
			<bndbox>
				<xmin>208</xmin>
				<ymin>477</ymin>
				<xmax>239</xmax>
				<ymax>501</ymax>
			</bndbox>
		</object>
	</annotation>
