<?xml version="1.0" encoding="utf-8"?>
	<annotation>
		<folder>driving_annotation_dataset</folder>
		<filename>9999955_00000_d_0000159.jpg</filename>
		<size>
			<width>1400</width>
			<height>788</height>
			<depth>3</depth>
		</size>
		<object>
			<name>van</name>
			<pose>Unspecified</pose>
			<truncated>0</truncated>
			<difficult>0</difficult>
			<bndbox>
				<xmin>210</xmin>
				<ymin>411</ymin>
				<xmax>308</xmax>
				<ymax>480</ymax>
			</bndbox>
		</object>
		<object>
			<name>car</name>
			<pose>Unspecified</pose>
			<truncated>0</truncated>
			<difficult>0</difficult>
			<bndbox>
				<xmin>510</xmin>
				<ymin>238</ymin>
				<xmax>577</xmax>
				<ymax>281</ymax>
			</bndbox>
		</object>
		<object>
			<name>car</name>
			<pose>Unspecified</pose>
			<truncated>0</truncated>
			<difficult>0</difficult>
			<bndbox>
				<xmin>611</xmin>
				<ymin>387</ymin>
				<xmax>687</xmax>
				<ymax>456</ymax>
			</bndbox>
		</object>
		<object>
			<name>car</name>
			<pose>Unspecified</pose>
			<truncated>0</truncated>
			<difficult>0</difficult>
			<bndbox>
				<xmin>604</xmin>
				<ymin>221</ymin>
				<xmax>669</xmax>
				<ymax>267</ymax>
			</bndbox>
		</object>
	</annotation>
