<?xml version="1.0" encoding="utf-8"?>
	<annotation>
		<folder>driving_annotation_dataset</folder>
		<filename>9999943_00000_d_0000006.jpg</filename>
		<size>
			<width>1400</width>
			<height>1050</height>
			<depth>3</depth>
		</size>
		<object>
			<name>bus</name>
			<pose>Unspecified</pose>
			<truncated>0</truncated>
			<difficult>0</difficult>
			<bndbox>
				<xmin>116</xmin>
				<ymin>200</ymin>
				<xmax>186</xmax>
				<ymax>317</ymax>
			</bndbox>
		</object>
		<object>
			<name>bus</name>
			<pose>Unspecified</pose>
			<truncated>0</truncated>
			<difficult>0</difficult>
			<bndbox>
				<xmin>195</xmin>
				<ymin>205</ymin>
				<xmax>263</xmax>
				<ymax>316</ymax>
			</bndbox>
		</object>
		<object>
			<name>bus</name>
			<pose>Unspecified</pose>
			<truncated>0</truncated>
			<difficult>0</difficult>
			<bndbox>
				<xmin>286</xmin>
				<ymin>139</ymin>
				<xmax>367</xmax>
				<ymax>239</ymax>
			</bndbox>
		</object>
		<object>
			<name>bus</name>
			<pose>Unspecified</pose>
			<truncated>0</truncated>
			<difficult>0</difficult>
			<bndbox>
				<xmin>157</xmin>
				<ymin>128</ymin>
				<xmax>276</xmax>
				<ymax>230</ymax>
			</bndbox>
		</object>
		<object>
			<name>bus</name>
			<pose>Unspecified</pose>
			<truncated>0</truncated>
			<difficult>0</difficult>
			<bndbox>
				<xmin>375</xmin>
				<ymin>144</ymin>
				<xmax>439</xmax>
				<ymax>257</ymax>
			</bndbox>
		</object>
		<object>
			<name>bus</name>
			<pose>Unspecified</pose>
			<truncated>0</truncated>
			<difficult>0</difficult>
			<bndbox>
				<xmin>438</xmin>
				<ymin>149</ymin>
				<xmax>494</xmax>
				<ymax>256</ymax>
			</bndbox>
		</object>
		<object>
			<name>bus</name>
			<pose>Unspecified</pose>
			<truncated>0</truncated>
			<difficult>0</difficult>
			<bndbox>
				<xmin>417</xmin>
				<ymin>9</ymin>
				<xmax>466</xmax>
				<ymax>85</ymax>
			</bndbox>
		</object>
		<object>
			<name>bus</name>
			<pose>Unspecified</pose>
			<truncated>0</truncated>
			<difficult>0</difficult>
			<bndbox>
				<xmin>376</xmin>
				<ymin>242</ymin>
				<xmax>505</xmax>
				<ymax>399</ymax>
			</bndbox>
		</object>
		<object>
			<name>bus</name>
			<pose>Unspecified</pose>
			<truncated>0</truncated>
			<difficult>0</difficult>
			<bndbox>
				<xmin>508</xmin>
				<ymin>22</ymin>
				<xmax>548</xmax>
				<ymax>88</ymax>
			</bndbox>
		</object>
		<object>
			<name>bus</name>
			<pose>Unspecified</pose>
			<truncated>0</truncated>
			<difficult>0</difficult>
			<bndbox>
				<xmin>468</xmin>
				<ymin>10</ymin>
				<xmax>504</xmax>
				<ymax>75</ymax>
			</bndbox>
		</object>
		<object>
			<name>car</name>
			<pose>Unspecified</pose>
			<truncated>0</truncated>
			<difficult>0</difficult>
			<bndbox>
				<xmin>611</xmin>
				<ymin>1</ymin>
				<xmax>650</xmax>
				<ymax>15</ymax>
			</bndbox>
		</object>
		<object>
			<name>car</name>
			<pose>Unspecified</pose>
			<truncated>0</truncated>
			<difficult>0</difficult>
			<bndbox>
				<xmin>614</xmin>
				<ymin>24</ymin>
				<xmax>635</xmax>
				<ymax>46</ymax>
			</bndbox>
		</object>
		<object>
			<name>car</name>
			<pose>Unspecified</pose>
			<truncated>0</truncated>
			<difficult>0</difficult>
			<bndbox>
				<xmin>650</xmin>
				<ymin>20</ymin>
				<xmax>675</xmax>
				<ymax>44</ymax>
			</bndbox>
		</object>
		<object>
			<name>car</name>
			<pose>Unspecified</pose>
			<truncated>0</truncated>
			<difficult>0</difficult>
			<bndbox>
				<xmin>634</xmin>
				<ymin>139</ymin>
				<xmax>660</xmax>
				<ymax>176</ymax>
			</bndbox>
		</object>
		<object>
			<name>car</name>
			<pose>Unspecified</pose>
			<truncated>0</truncated>
			<difficult>0</difficult>
			<bndbox>
				<xmin>620</xmin>
				<ymin>94</ymin>
				<xmax>643</xmax>
				<ymax>117</ymax>
			</bndbox>
		</object>
		<object>
			<name>car</name>
			<pose>Unspecified</pose>
			<truncated>0</truncated>
			<difficult>0</difficult>
			<bndbox>
				<xmin>620</xmin>
				<ymin>73</ymin>
				<xmax>641</xmax>
				<ymax>95</ymax>
			</bndbox>
		</object>
		<object>
			<name>bus</name>
			<pose>Unspecified</pose>
			<truncated>0</truncated>
			<difficult>0</difficult>
			<bndbox>
				<xmin>636</xmin>
				<ymin>175</ymin>
				<xmax>696</xmax>
				<ymax>304</ymax>
			</bndbox>
		</object>
		<object>
			<name>bus</name>
			<pose>Unspecified</pose>
			<truncated>0</truncated>
			<difficult>0</difficult>
			<bndbox>
				<xmin>634</xmin>
				<ymin>319</ymin>
				<xmax>699</xmax>
				<ymax>485</ymax>
			</bndbox>
		</object>
		<object>
			<name>people</name>
			<pose>Unspecified</pose>
			<truncated>0</truncated>
			<difficult>0</difficult>
			<bndbox>
				<xmin>209</xmin>
				<ymin>432</ymin>
				<xmax>225</xmax>
				<ymax>445</ymax>
			</bndbox>
		</object>
		<object>
			<name>people</name>
			<pose>Unspecified</pose>
			<truncated>0</truncated>
			<difficult>0</difficult>
			<bndbox>
				<xmin>204</xmin>
				<ymin>444</ymin>
				<xmax>219</xmax>
				<ymax>460</ymax>
			</bndbox>
		</object>
		<object>
			<name>people</name>
			<pose>Unspecified</pose>
			<truncated>0</truncated>
			<difficult>0</difficult>
			<bndbox>
				<xmin>284</xmin>
				<ymin>473</ymin>
				<xmax>298</xmax>
				<ymax>495</ymax>
			</bndbox>
		</object>
		<object>
			<name>people</name>
			<pose>Unspecified</pose>
			<truncated>0</truncated>
			<difficult>0</difficult>
			<bndbox>
				<xmin>280</xmin>
				<ymin>469</ymin>
				<xmax>301</xmax>
				<ymax>486</ymax>
			</bndbox>
		</object>
		<object>
			<name>pedestrian</name>
			<pose>Unspecified</pose>
			<truncated>0</truncated>
			<difficult>0</difficult>
			<bndbox>
				<xmin>275</xmin>
				<ymin>479</ymin>
				<xmax>293</xmax>
				<ymax>508</ymax>
			</bndbox>
		</object>
		<object>
			<name>pedestrian</name>
			<pose>Unspecified</pose>
			<truncated>0</truncated>
			<difficult>0</difficult>
			<bndbox>
				<xmin>274</xmin>
				<ymin>447</ymin>
				<xmax>288</xmax>
				<ymax>472</ymax>
			</bndbox>
		</object>
		<object>
			<name>pedestrian</name>
			<pose>Unspecified</pose>
			<truncated>0</truncated>
			<difficult>0</difficult>
			<bndbox>
				<xmin>195</xmin>
				<ymin>415</ymin>
				<xmax>212</xmax>
				<ymax>447</ymax>
			</bndbox>
		</object>
		<object>
			<name>pedestrian</name>
			<pose>Unspecified</pose>
			<truncated>0</truncated>
			<difficult>0</difficult>
			<bndbox>
				<xmin>212</xmin>
				<ymin>409</ymin>
				<xmax>230</xmax>
				<ymax>441</ymax>
			</bndbox>
		</object>
		<object>
			<name>bicycle</name>
			<pose>Unspecified</pose>
			<truncated>0</truncated>
			<difficult>0</difficult>
			<bndbox>
				<xmin>289</xmin>
				<ymin>561</ymin>
				<xmax>334</xmax>
				<ymax>579</ymax>
			</bndbox>
		</object>
		<object>
			<name>pedestrian</name>
			<pose>Unspecified</pose>
			<truncated>0</truncated>
			<difficult>0</difficult>
			<bndbox>
				<xmin>639</xmin>
				<ymin>289</ymin>
				<xmax>650</xmax>
				<ymax>320</ymax>
			</bndbox>
		</object>
		<object>
			<name>pedestrian</name>
			<pose>Unspecified</pose>
			<truncated>0</truncated>
			<difficult>0</difficult>
			<bndbox>
				<xmin>684</xmin>
				<ymin>486</ymin>
				<xmax>698</xmax>
				<ymax>523</ymax>
			</bndbox>
		</object>
		<object>
			<name>motor</name>
			<pose>Unspecified</pose>
			<truncated>0</truncated>
			<difficult>0</difficult>
			<bndbox>
				<xmin>692</xmin>
				<ymin>378</ymin>
				<xmax>702</xmax>
				<ymax>410</ymax>
			</bndbox>
		</object>
		<object>
			<name>bicycle</name>
			<pose>Unspecified</pose>
			<truncated>0</truncated>
			<difficult>0</difficult>
			<bndbox>
				<xmin>720</xmin>
				<ymin>359</ymin>
				<xmax>731</xmax>
				<ymax>388</ymax>
			</bndbox>
		</object>
		<object>
			<name>motor</name>
			<pose>Unspecified</pose>
			<truncated>0</truncated>
			<difficult>0</difficult>
			<bndbox>
				<xmin>708</xmin>
				<ymin>476</ymin>
				<xmax>723</xmax>
				<ymax>512</ymax>
			</bndbox>
		</object>
		<object>
			<name>motor</name>
			<pose>Unspecified</pose>
			<truncated>0</truncated>
			<difficult>0</difficult>
			<bndbox>
				<xmin>797</xmin>
				<ymin>524</ymin>
				<xmax>835</xmax>
				<ymax>558</ymax>
			</bndbox>
		</object>
		<object>
			<name>people</name>
			<pose>Unspecified</pose>
			<truncated>0</truncated>
			<difficult>0</difficult>
			<bndbox>
				<xmin>806</xmin>
				<ymin>519</ymin>
				<xmax>819</xmax>
				<ymax>537</ymax>
			</bndbox>
		</object>
		<object>
			<name>people</name>
			<pose>Unspecified</pose>
			<truncated>0</truncated>
			<difficult>0</difficult>
			<bndbox>
				<xmin>709</xmin>
				<ymin>475</ymin>
				<xmax>722</xmax>
				<ymax>497</ymax>
			</bndbox>
		</object>
		<object>
			<name>awning-tricycle</name>
			<pose>Unspecified</pose>
			<truncated>0</truncated>
			<difficult>0</difficult>
			<bndbox>
				<xmin>733</xmin>
				<ymin>470</ymin>
				<xmax>810</xmax>
				<ymax>518</ymax>
			</bndbox>
		</object>
		<object>
			<name>truck</name>
			<pose>Unspecified</pose>
			<truncated>0</truncated>
			<difficult>0</difficult>
			<bndbox>
				<xmin>1315</xmin>
				<ymin>97</ymin>
				<xmax>1365</xmax>
				<ymax>140</ymax>
			</bndbox>
		</object>
		<object>
			<name>car</name>
			<pose>Unspecified</pose>
			<truncated>0</truncated>
			<difficult>0</difficult>
			<bndbox>
				<xmin>1287</xmin>
				<ymin>105</ymin>
				<xmax>1316</xmax>
				<ymax>138</ymax>
			</bndbox>
		</object>
		<object>
			<name>van</name>
			<pose>Unspecified</pose>
			<truncated>0</truncated>
			<difficult>0</difficult>
			<bndbox>
				<xmin>1271</xmin>
				<ymin>108</ymin>
				<xmax>1298</xmax>
				<ymax>134</ymax>
			</bndbox>
		</object>
		<object>
			<name>truck</name>
			<pose>Unspecified</pose>
			<truncated>0</truncated>
			<difficult>0</difficult>
			<bndbox>
				<xmin>1188</xmin>
				<ymin>70</ymin>
				<xmax>1276</xmax>
				<ymax>132</ymax>
			</bndbox>
		</object>
		<object>
			<name>van</name>
			<pose>Unspecified</pose>
			<truncated>0</truncated>
			<difficult>0</difficult>
			<bndbox>
				<xmin>1147</xmin>
				<ymin>99</ymin>
				<xmax>1200</xmax>
				<ymax>128</ymax>
			</bndbox>
		</object>
		<object>
			<name>pedestrian</name>
			<pose>Unspecified</pose>
			<truncated>0</truncated>
			<difficult>0</difficult>
			<bndbox>
				<xmin>1334</xmin>
				<ymin>450</ymin>
				<xmax>1354</xmax>
				<ymax>480</ymax>
			</bndbox>
		</object>
		<object>
			<name>van</name>
			<pose>Unspecified</pose>
			<truncated>0</truncated>
			<difficult>0</difficult>
			<bndbox>
				<xmin>1206</xmin>
				<ymin>594</ymin>
				<xmax>1323</xmax>
				<ymax>652</ymax>
			</bndbox>
		</object>
		<object>
			<name>car</name>
			<pose>Unspecified</pose>
			<truncated>0</truncated>
			<difficult>0</difficult>
			<bndbox>
				<xmin>1305</xmin>
				<ymin>648</ymin>
				<xmax>1400</xmax>
				<ymax>718</ymax>
			</bndbox>
		</object>
	</annotation>
