<?xml version="1.0" encoding="utf-8"?>
	<annotation>
		<folder>driving_annotation_dataset</folder>
		<filename>9999998_00364_d_0000316.jpg</filename>
		<size>
			<width>2000</width>
			<height>1500</height>
			<depth>3</depth>
		</size>
		<object>
			<name>car</name>
			<pose>Unspecified</pose>
			<truncated>0</truncated>
			<difficult>0</difficult>
			<bndbox>
				<xmin>884</xmin>
				<ymin>1041</ymin>
				<xmax>1206</xmax>
				<ymax>1183</ymax>
			</bndbox>
		</object>
		<object>
			<name>car</name>
			<pose>Unspecified</pose>
			<truncated>0</truncated>
			<difficult>0</difficult>
			<bndbox>
				<xmin>1</xmin>
				<ymin>1109</ymin>
				<xmax>119</xmax>
				<ymax>1268</ymax>
			</bndbox>
		</object>
		<object>
			<name>car</name>
			<pose>Unspecified</pose>
			<truncated>0</truncated>
			<difficult>0</difficult>
			<bndbox>
				<xmin>23</xmin>
				<ymin>825</ymin>
				<xmax>276</xmax>
				<ymax>946</ymax>
			</bndbox>
		</object>
		<object>
			<name>car</name>
			<pose>Unspecified</pose>
			<truncated>0</truncated>
			<difficult>0</difficult>
			<bndbox>
				<xmin>405</xmin>
				<ymin>843</ymin>
				<xmax>681</xmax>
				<ymax>976</ymax>
			</bndbox>
		</object>
		<object>
			<name>car</name>
			<pose>Unspecified</pose>
			<truncated>0</truncated>
			<difficult>0</difficult>
			<bndbox>
				<xmin>375</xmin>
				<ymin>741</ymin>
				<xmax>631</xmax>
				<ymax>871</ymax>
			</bndbox>
		</object>
		<object>
			<name>car</name>
			<pose>Unspecified</pose>
			<truncated>0</truncated>
			<difficult>0</difficult>
			<bndbox>
				<xmin>709</xmin>
				<ymin>710</ymin>
				<xmax>956</xmax>
				<ymax>824</ymax>
			</bndbox>
		</object>
		<object>
			<name>car</name>
			<pose>Unspecified</pose>
			<truncated>0</truncated>
			<difficult>0</difficult>
			<bndbox>
				<xmin>984</xmin>
				<ymin>695</ymin>
				<xmax>1223</xmax>
				<ymax>800</ymax>
			</bndbox>
		</object>
		<object>
			<name>pedestrian</name>
			<pose>Unspecified</pose>
			<truncated>0</truncated>
			<difficult>0</difficult>
			<bndbox>
				<xmin>1194</xmin>
				<ymin>715</ymin>
				<xmax>1251</xmax>
				<ymax>790</ymax>
			</bndbox>
		</object>
		<object>
			<name>pedestrian</name>
			<pose>Unspecified</pose>
			<truncated>0</truncated>
			<difficult>0</difficult>
			<bndbox>
				<xmin>1087</xmin>
				<ymin>664</ymin>
				<xmax>1114</xmax>
				<ymax>711</ymax>
			</bndbox>
		</object>
		<object>
			<name>car</name>
			<pose>Unspecified</pose>
			<truncated>0</truncated>
			<difficult>0</difficult>
			<bndbox>
				<xmin>1234</xmin>
				<ymin>668</ymin>
				<xmax>1480</xmax>
				<ymax>785</ymax>
			</bndbox>
		</object>
		<object>
			<name>car</name>
			<pose>Unspecified</pose>
			<truncated>0</truncated>
			<difficult>0</difficult>
			<bndbox>
				<xmin>1348</xmin>
				<ymin>646</ymin>
				<xmax>1537</xmax>
				<ymax>744</ymax>
			</bndbox>
		</object>
		<object>
			<name>car</name>
			<pose>Unspecified</pose>
			<truncated>0</truncated>
			<difficult>0</difficult>
			<bndbox>
				<xmin>1487</xmin>
				<ymin>618</ymin>
				<xmax>1708</xmax>
				<ymax>703</ymax>
			</bndbox>
		</object>
		<object>
			<name>car</name>
			<pose>Unspecified</pose>
			<truncated>0</truncated>
			<difficult>0</difficult>
			<bndbox>
				<xmin>1678</xmin>
				<ymin>709</ymin>
				<xmax>1859</xmax>
				<ymax>816</ymax>
			</bndbox>
		</object>
		<object>
			<name>car</name>
			<pose>Unspecified</pose>
			<truncated>0</truncated>
			<difficult>0</difficult>
			<bndbox>
				<xmin>1778</xmin>
				<ymin>627</ymin>
				<xmax>1956</xmax>
				<ymax>715</ymax>
			</bndbox>
		</object>
		<object>
			<name>car</name>
			<pose>Unspecified</pose>
			<truncated>0</truncated>
			<difficult>0</difficult>
			<bndbox>
				<xmin>1712</xmin>
				<ymin>585</ymin>
				<xmax>1901</xmax>
				<ymax>652</ymax>
			</bndbox>
		</object>
		<object>
			<name>car</name>
			<pose>Unspecified</pose>
			<truncated>0</truncated>
			<difficult>0</difficult>
			<bndbox>
				<xmin>1894</xmin>
				<ymin>545</ymin>
				<xmax>2001</xmax>
				<ymax>632</ymax>
			</bndbox>
		</object>
		<object>
			<name>car</name>
			<pose>Unspecified</pose>
			<truncated>0</truncated>
			<difficult>0</difficult>
			<bndbox>
				<xmin>1745</xmin>
				<ymin>501</ymin>
				<xmax>1887</xmax>
				<ymax>571</ymax>
			</bndbox>
		</object>
		<object>
			<name>pedestrian</name>
			<pose>Unspecified</pose>
			<truncated>0</truncated>
			<difficult>0</difficult>
			<bndbox>
				<xmin>1720</xmin>
				<ymin>479</ymin>
				<xmax>1739</xmax>
				<ymax>536</ymax>
			</bndbox>
		</object>
		<object>
			<name>motor</name>
			<pose>Unspecified</pose>
			<truncated>0</truncated>
			<difficult>0</difficult>
			<bndbox>
				<xmin>120</xmin>
				<ymin>715</ymin>
				<xmax>145</xmax>
				<ymax>759</ymax>
			</bndbox>
		</object>
		<object>
			<name>motor</name>
			<pose>Unspecified</pose>
			<truncated>0</truncated>
			<difficult>0</difficult>
			<bndbox>
				<xmin>116</xmin>
				<ymin>697</ymin>
				<xmax>149</xmax>
				<ymax>744</ymax>
			</bndbox>
		</object>
		<object>
			<name>bicycle</name>
			<pose>Unspecified</pose>
			<truncated>0</truncated>
			<difficult>0</difficult>
			<bndbox>
				<xmin>649</xmin>
				<ymin>629</ymin>
				<xmax>695</xmax>
				<ymax>680</ymax>
			</bndbox>
		</object>
		<object>
			<name>bicycle</name>
			<pose>Unspecified</pose>
			<truncated>0</truncated>
			<difficult>0</difficult>
			<bndbox>
				<xmin>704</xmin>
				<ymin>631</ymin>
				<xmax>731</xmax>
				<ymax>688</ymax>
			</bndbox>
		</object>
		<object>
			<name>motor</name>
			<pose>Unspecified</pose>
			<truncated>0</truncated>
			<difficult>0</difficult>
			<bndbox>
				<xmin>825</xmin>
				<ymin>610</ymin>
				<xmax>848</xmax>
				<ymax>660</ymax>
			</bndbox>
		</object>
		<object>
			<name>motor</name>
			<pose>Unspecified</pose>
			<truncated>0</truncated>
			<difficult>0</difficult>
			<bndbox>
				<xmin>896</xmin>
				<ymin>594</ymin>
				<xmax>931</xmax>
				<ymax>649</ymax>
			</bndbox>
		</object>
		<object>
			<name>pedestrian</name>
			<pose>Unspecified</pose>
			<truncated>0</truncated>
			<difficult>0</difficult>
			<bndbox>
				<xmin>1885</xmin>
				<ymin>458</ymin>
				<xmax>1914</xmax>
				<ymax>509</ymax>
			</bndbox>
		</object>
		<object>
			<name>motor</name>
			<pose>Unspecified</pose>
			<truncated>0</truncated>
			<difficult>0</difficult>
			<bndbox>
				<xmin>1627</xmin>
				<ymin>503</ymin>
				<xmax>1662</xmax>
				<ymax>551</ymax>
			</bndbox>
		</object>
		<object>
			<name>pedestrian</name>
			<pose>Unspecified</pose>
			<truncated>0</truncated>
			<difficult>0</difficult>
			<bndbox>
				<xmin>1323</xmin>
				<ymin>502</ymin>
				<xmax>1350</xmax>
				<ymax>568</ymax>
			</bndbox>
		</object>
		<object>
			<name>car</name>
			<pose>Unspecified</pose>
			<truncated>0</truncated>
			<difficult>0</difficult>
			<bndbox>
				<xmin>1577</xmin>
				<ymin>207</ymin>
				<xmax>1634</xmax>
				<ymax>241</ymax>
			</bndbox>
		</object>
		<object>
			<name>van</name>
			<pose>Unspecified</pose>
			<truncated>0</truncated>
			<difficult>0</difficult>
			<bndbox>
				<xmin>1537</xmin>
				<ymin>195</ymin>
				<xmax>1577</xmax>
				<ymax>229</ymax>
			</bndbox>
		</object>
		<object>
			<name>car</name>
			<pose>Unspecified</pose>
			<truncated>0</truncated>
			<difficult>0</difficult>
			<bndbox>
				<xmin>1508</xmin>
				<ymin>197</ymin>
				<xmax>1546</xmax>
				<ymax>221</ymax>
			</bndbox>
		</object>
		<object>
			<name>car</name>
			<pose>Unspecified</pose>
			<truncated>0</truncated>
			<difficult>0</difficult>
			<bndbox>
				<xmin>1443</xmin>
				<ymin>181</ymin>
				<xmax>1489</xmax>
				<ymax>205</ymax>
			</bndbox>
		</object>
		<object>
			<name>van</name>
			<pose>Unspecified</pose>
			<truncated>0</truncated>
			<difficult>0</difficult>
			<bndbox>
				<xmin>1420</xmin>
				<ymin>165</ymin>
				<xmax>1468</xmax>
				<ymax>199</ymax>
			</bndbox>
		</object>
		<object>
			<name>truck</name>
			<pose>Unspecified</pose>
			<truncated>0</truncated>
			<difficult>0</difficult>
			<bndbox>
				<xmin>1390</xmin>
				<ymin>150</ymin>
				<xmax>1440</xmax>
				<ymax>190</ymax>
			</bndbox>
		</object>
		<object>
			<name>car</name>
			<pose>Unspecified</pose>
			<truncated>0</truncated>
			<difficult>0</difficult>
			<bndbox>
				<xmin>1372</xmin>
				<ymin>157</ymin>
				<xmax>1414</xmax>
				<ymax>183</ymax>
			</bndbox>
		</object>
		<object>
			<name>car</name>
			<pose>Unspecified</pose>
			<truncated>0</truncated>
			<difficult>0</difficult>
			<bndbox>
				<xmin>1223</xmin>
				<ymin>126</ymin>
				<xmax>1262</xmax>
				<ymax>148</ymax>
			</bndbox>
		</object>
		<object>
			<name>van</name>
			<pose>Unspecified</pose>
			<truncated>0</truncated>
			<difficult>0</difficult>
			<bndbox>
				<xmin>1206</xmin>
				<ymin>115</ymin>
				<xmax>1239</xmax>
				<ymax>135</ymax>
			</bndbox>
		</object>
		<object>
			<name>van</name>
			<pose>Unspecified</pose>
			<truncated>0</truncated>
			<difficult>0</difficult>
			<bndbox>
				<xmin>1097</xmin>
				<ymin>88</ymin>
				<xmax>1131</xmax>
				<ymax>109</ymax>
			</bndbox>
		</object>
	</annotation>
