<?xml version="1.0" encoding="utf-8"?>
	<annotation>
		<folder>driving_annotation_dataset</folder>
		<filename>9999962_00000_d_0000045.jpg</filename>
		<size>
			<width>1400</width>
			<height>1050</height>
			<depth>3</depth>
		</size>
		<object>
			<name>van</name>
			<pose>Unspecified</pose>
			<truncated>0</truncated>
			<difficult>0</difficult>
			<bndbox>
				<xmin>391</xmin>
				<ymin>895</ymin>
				<xmax>464</xmax>
				<ymax>1037</ymax>
			</bndbox>
		</object>
		<object>
			<name>car</name>
			<pose>Unspecified</pose>
			<truncated>0</truncated>
			<difficult>0</difficult>
			<bndbox>
				<xmin>898</xmin>
				<ymin>913</ymin>
				<xmax>1070</xmax>
				<ymax>1004</ymax>
			</bndbox>
		</object>
		<object>
			<name>car</name>
			<pose>Unspecified</pose>
			<truncated>0</truncated>
			<difficult>0</difficult>
			<bndbox>
				<xmin>782</xmin>
				<ymin>700</ymin>
				<xmax>877</xmax>
				<ymax>860</ymax>
			</bndbox>
		</object>
		<object>
			<name>car</name>
			<pose>Unspecified</pose>
			<truncated>0</truncated>
			<difficult>0</difficult>
			<bndbox>
				<xmin>838</xmin>
				<ymin>466</ymin>
				<xmax>981</xmax>
				<ymax>585</ymax>
			</bndbox>
		</object>
		<object>
			<name>car</name>
			<pose>Unspecified</pose>
			<truncated>0</truncated>
			<difficult>0</difficult>
			<bndbox>
				<xmin>937</xmin>
				<ymin>123</ymin>
				<xmax>1064</xmax>
				<ymax>245</ymax>
			</bndbox>
		</object>
		<object>
			<name>car</name>
			<pose>Unspecified</pose>
			<truncated>0</truncated>
			<difficult>0</difficult>
			<bndbox>
				<xmin>974</xmin>
				<ymin>174</ymin>
				<xmax>1107</xmax>
				<ymax>315</ymax>
			</bndbox>
		</object>
		<object>
			<name>car</name>
			<pose>Unspecified</pose>
			<truncated>0</truncated>
			<difficult>0</difficult>
			<bndbox>
				<xmin>727</xmin>
				<ymin>49</ymin>
				<xmax>788</xmax>
				<ymax>167</ymax>
			</bndbox>
		</object>
		<object>
			<name>van</name>
			<pose>Unspecified</pose>
			<truncated>0</truncated>
			<difficult>0</difficult>
			<bndbox>
				<xmin>721</xmin>
				<ymin>205</ymin>
				<xmax>786</xmax>
				<ymax>363</ymax>
			</bndbox>
		</object>
		<object>
			<name>van</name>
			<pose>Unspecified</pose>
			<truncated>0</truncated>
			<difficult>0</difficult>
			<bndbox>
				<xmin>729</xmin>
				<ymin>407</ymin>
				<xmax>785</xmax>
				<ymax>528</ymax>
			</bndbox>
		</object>
		<object>
			<name>van</name>
			<pose>Unspecified</pose>
			<truncated>0</truncated>
			<difficult>0</difficult>
			<bndbox>
				<xmin>621</xmin>
				<ymin>350</ymin>
				<xmax>681</xmax>
				<ymax>481</ymax>
			</bndbox>
		</object>
		<object>
			<name>car</name>
			<pose>Unspecified</pose>
			<truncated>0</truncated>
			<difficult>0</difficult>
			<bndbox>
				<xmin>409</xmin>
				<ymin>431</ymin>
				<xmax>483</xmax>
				<ymax>594</ymax>
			</bndbox>
		</object>
		<object>
			<name>car</name>
			<pose>Unspecified</pose>
			<truncated>0</truncated>
			<difficult>0</difficult>
			<bndbox>
				<xmin>416</xmin>
				<ymin>259</ymin>
				<xmax>487</xmax>
				<ymax>403</ymax>
			</bndbox>
		</object>
		<object>
			<name>pedestrian</name>
			<pose>Unspecified</pose>
			<truncated>0</truncated>
			<difficult>0</difficult>
			<bndbox>
				<xmin>897</xmin>
				<ymin>760</ymin>
				<xmax>925</xmax>
				<ymax>780</ymax>
			</bndbox>
		</object>
		<object>
			<name>pedestrian</name>
			<pose>Unspecified</pose>
			<truncated>0</truncated>
			<difficult>0</difficult>
			<bndbox>
				<xmin>1045</xmin>
				<ymin>509</ymin>
				<xmax>1070</xmax>
				<ymax>533</ymax>
			</bndbox>
		</object>
		<object>
			<name>pedestrian</name>
			<pose>Unspecified</pose>
			<truncated>0</truncated>
			<difficult>0</difficult>
			<bndbox>
				<xmin>1137</xmin>
				<ymin>709</ymin>
				<xmax>1175</xmax>
				<ymax>735</ymax>
			</bndbox>
		</object>
		<object>
			<name>pedestrian</name>
			<pose>Unspecified</pose>
			<truncated>0</truncated>
			<difficult>0</difficult>
			<bndbox>
				<xmin>1168</xmin>
				<ymin>723</ymin>
				<xmax>1201</xmax>
				<ymax>739</ymax>
			</bndbox>
		</object>
		<object>
			<name>car</name>
			<pose>Unspecified</pose>
			<truncated>0</truncated>
			<difficult>0</difficult>
			<bndbox>
				<xmin>1309</xmin>
				<ymin>758</ymin>
				<xmax>1401</xmax>
				<ymax>838</ymax>
			</bndbox>
		</object>
		<object>
			<name>car</name>
			<pose>Unspecified</pose>
			<truncated>0</truncated>
			<difficult>0</difficult>
			<bndbox>
				<xmin>1282</xmin>
				<ymin>411</ymin>
				<xmax>1401</xmax>
				<ymax>573</ymax>
			</bndbox>
		</object>
	</annotation>
